compare/__init__.py
compare/core/__init__.py
compare/core/compare_face.py
compare/services/__init__.py
compare/services/base_service.py
compare/services/detection_service.py
compare/services/recognition_service.py
compare/services/server_api_list.py
compare/services/verification_service.py
compreface_sdk_python-1.0.6.dist-info/LICENSE
compreface_sdk_python-1.0.6.dist-info/METADATA
compreface_sdk_python-1.0.6.dist-info/WHEEL
compreface_sdk_python-1.0.6.dist-info/top_level.txt
compreface_sdk_python-1.0.6.dist-info/RECORD
