Metadata-Version: 2.1
Name: compreface-sdk-python
Version: 1.0.6
Summary: 'CompareFace Python SDK
Home-page: https://github.com/zyk-miao/-compreface-sdk-python.git
Author: yukai bill
Author-email: yukaibill@gmail.com
License: Apache License 2.0
Classifier: License :: OSI Approved :: Apache Software License
Classifier: Programming Language :: Python
Classifier: Programming Language :: Python :: 3
Requires-Python: >=3.6
License-File: LICENSE
Requires-Dist: httpx
Requires-Dist: aiofiles
